terminalchat/__init__.py
terminalchat/__main__.py
terminalchat/client.py
terminalchat/config.py
terminalchat/main.py
gupsup-1.1.0.dist-info/METADATA
gupsup-1.1.0.dist-info/WHEEL
gupsup-1.1.0.dist-info/entry_points.txt
gupsup-1.1.0.dist-info/top_level.txt
gupsup-1.1.0.dist-info/RECORD
