Metadata-Version: 2.4
Name: gupsup
Version: 1.1.0
Summary: Secure terminal-based chat application with image sharing for real-time communication
Home-page: https://github.com/iamRahul21/terminalchat
Author: Rahul Deka
Author-email: Rahul Deka <rahuldeka072@gmail.com>
Project-URL: Homepage, https://github.com/iamRahul21/terminalchat
Project-URL: Repository, https://github.com/iamRahul21/terminalchat
Project-URL: Issues, https://github.com/iamRahul21/terminalchat/issues
Keywords: chat,terminal,websocket,real-time
Classifier: Development Status :: 4 - Beta
Classifier: Intended Audience :: End Users/Desktop
Classifier: License :: OSI Approved :: MIT License
Classifier: Programming Language :: Python :: 3
Classifier: Programming Language :: Python :: 3.8
Classifier: Programming Language :: Python :: 3.9
Classifier: Programming Language :: Python :: 3.10
Classifier: Programming Language :: Python :: 3.11
Classifier: Programming Language :: Python :: 3.12
Requires-Python: >=3.8
Requires-Dist: websockets>=11.0
Requires-Dist: cryptography>=3.0.0
Dynamic: author
Dynamic: home-page
Dynamic: requires-python
